{
  "_status": "ok",
  "ticker": "603233.SH",
  "fetched_at": "2026-07-17T10:20:03Z",
  "api_used": "report_rc",
  "_attempted_endpoints": [
    "broker_recommend",
    "report_rc"
  ],
  "window_days": 90,
  "recommendations": [
    {
      "ts_code": "603233.SH",
      "name": "大参林",
      "report_date": "20260629",
      "report_title": "Dashenlin：China＿Healthcare＿Corporate＿Day＿2026＿Takeaways",
      "report_type": "点评",
      "classify": "一般报告",
      "org_name": "高盛集团（GoldmanSachs）",
      "author_name": "闫天一,Ziyi Chen,郑雪轩",
      "quarter": "2026Q2",
      "op_rt": null,
      "op_pr": null,
      "tp": null,
      "np": null,
      "eps": 0.59,
      "pe": null,
      "rd": null,
      "roe": null,
      "ev_ebitda": null,
      "rating": "Buy",
      "max_price": null,
      "min_price": 25.0,
      "rec_date": "20260629",
      "broker": "高盛集团（GoldmanSachs）",
      "analyst": null,
      "recommendation": "Buy",
      "target_price": null,
      "report_id": null
    },
    {
      "ts_code": "603233.SH",
      "name": "大参林",
      "report_date": "20260629",
      "report_title": "Dashenlin：China＿Healthcare＿Corporate＿Day＿2026＿Takeaways",
      "report_type": "点评",
      "classify": "一般报告",
      "org_name": "高盛集团（GoldmanSachs）",
      "author_name": "闫天一,Ziyi Chen,郑雪轩",
      "quarter": "2026Q4",
      "op_rt": 3057540.0,
      "op_pr": null,
      "tp": null,
      "np": null,
      "eps": 1.2,
      "pe": 12.3,
      "rd": 6.2,
      "roe": null,
      "ev_ebitda": null,
      "rating": "Buy",
      "max_price": null,
      "min_price": 25.0,
      "rec_date": "20260629",
      "broker": "高盛集团（GoldmanSachs）",
      "analyst": null,
      "recommendation": "Buy",
      "target_price": null,
      "report_id": null
    },
    {
      "ts_code": "603233.SH",
      "name": "大参林",
      "report_date": "20260629",
      "report_title": "Dashenlin：China＿Healthcare＿Corporate＿Day＿2026＿Takeaways",
      "report_type": "点评",
      "classify": "一般报告",
      "org_name": "高盛集团（GoldmanSachs）",
      "author_name": "闫天一,Ziyi Chen,郑雪轩",
      "quarter": "2027Q4",
      "op_rt": 3408220.0,
      "op_pr": null,
      "tp": null,
      "np": null,
      "eps": 1.37,
      "pe": 10.8,
      "rd": 7.1,
      "roe": null,
      "ev_ebitda": null,
      "rating": "Buy",
      "max_price": null,
      "min_price": 25.0,
      "rec_date": "20260629",
      "broker": "高盛集团（GoldmanSachs）",
      "analyst": null,
      "recommendation": "Buy",
      "target_price": null,
      "report_id": null
    },
    {
      "ts_code": "603233.SH",
      "name": "大参林",
      "report_date": "20260629",
      "report_title": "Dashenlin：China＿Healthcare＿Corporate＿Day＿2026＿Takeaways",
      "report_type": "点评",
      "classify": "一般报告",
      "org_name": "高盛集团（GoldmanSachs）",
      "author_name": "闫天一,Ziyi Chen,郑雪轩",
      "quarter": "2028Q4",
      "op_rt": 3706470.0,
      "op_pr": null,
      "tp": null,
      "np": null,
      "eps": 1.33,
      "pe": 11.1,
      "rd": 6.9,
      "roe": null,
      "ev_ebitda": null,
      "rating": "Buy",
      "max_price": null,
      "min_price": 25.0,
      "rec_date": "20260629",
      "broker": "高盛集团（GoldmanSachs）",
      "analyst": null,
      "recommendation": "Buy",
      "target_price": null,
      "report_id": null
    },
    {
      "ts_code": "603233.SH",
      "name": "大参林",
      "report_date": "20260601",
      "report_title": "大参林2026＿AIC：Q226扩张节奏加快，同店销售增速企稳",
      "report_type": "点评",
      "classify": "一般报告",
      "org_name": "UBS",
      "author_name": "刘嘉洲,陈晨,谢清竹",
      "quarter": "2026Q4",
      "op_rt": 2924800.0,
      "op_pr": null,
      "tp": null,
      "np": null,
      "eps": null,
      "pe": null,
      "rd": 5.0,
      "roe": null,
      "ev_ebitda": null,
      "rating": "买入",
      "max_price": null,
      "min_price": 26.7,
      "rec_date": "20260601",
      "broker": "UBS",
      "analyst": null,
      "recommendation": "买入",
      "target_price": null,
      "report_id": null
    },
    {
      "ts_code": "603233.SH",
      "name": "大参林",
      "report_date": "20260601",
      "report_title": "大参林2026＿AIC：Q226扩张节奏加快，同店销售增速企稳",
      "report_type": "点评",
      "classify": "一般报告",
      "org_name": "UBS",
      "author_name": "刘嘉洲,陈晨,谢清竹",
      "quarter": "2027Q4",
      "op_rt": 3207700.0,
      "op_pr": null,
      "tp": null,
      "np": null,
      "eps": null,
      "pe": null,
      "rd": 4.4,
      "roe": null,
      "ev_ebitda": null,
      "rating": "买入",
      "max_price": null,
      "min_price": 26.7,
      "rec_date": "20260601",
      "broker": "UBS",
      "analyst": null,
      "recommendation": "买入",
      "target_price": null,
      "report_id": null
    },
    {
      "ts_code": "603233.SH",
      "name": "大参林",
      "report_date": "20260601",
      "report_title": "大参林2026＿AIC：Q226扩张节奏加快，同店销售增速企稳",
      "report_type": "点评",
      "classify": "一般报告",
      "org_name": "UBS",
      "author_name": "刘嘉洲,陈晨,谢清竹",
      "quarter": "2028Q4",
      "op_rt": 3597300.0,
      "op_pr": null,
      "tp": null,
      "np": null,
      "eps": null,
      "pe": null,
      "rd": 5.1,
      "roe": null,
      "ev_ebitda": null,
      "rating": "买入",
      "max_price": null,
      "min_price": 26.7,
      "rec_date": "20260601",
      "broker": "UBS",
      "analyst": null,
      "recommendation": "买入",
      "target_price": null,
      "report_id": null
    },
    {
      "ts_code": "603233.SH",
      "name": "大参林",
      "report_date": "20260601",
      "report_title": "大参林2026＿AIC：Q226扩张节奏加快，同店销售增速企稳",
      "report_type": "点评",
      "classify": "一般报告",
      "org_name": "UBS",
      "author_name": "刘嘉洲,陈晨,谢清竹",
      "quarter": "2029Q4",
      "op_rt": 4035800.0,
      "op_pr": null,
      "tp": null,
      "np": null,
      "eps": null,
      "pe": null,
      "rd": 6.0,
      "roe": null,
      "ev_ebitda": null,
      "rating": "买入",
      "max_price": null,
      "min_price": 26.7,
      "rec_date": "20260601",
      "broker": "UBS",
      "analyst": null,
      "recommendation": "买入",
      "target_price": null,
      "report_id": null
    },
    {
      "ts_code": "603233.SH",
      "name": "大参林",
      "report_date": "20260513",
      "report_title": "大参林2025年报及2026年一季报点评：盈利能力持续改善，大举分红回报股东",
      "report_type": "点评",
      "classify": "一般报告",
      "org_name": "华创证券",
      "author_name": "郑辰,高初蕾",
      "quarter": "2026Q4",
      "op_rt": 2976000.0,
      "op_pr": null,
      "tp": 218300.0,
      "np": 145800.0,
      "eps": 1.28,
      "pe": 15.0,
      "rd": null,
      "roe": 18.8,
      "ev_ebitda": 9.0,
      "rating": "推荐",
      "max_price": null,
      "min_price": 25.6,
      "rec_date": "20260513",
      "broker": "华创证券",
      "analyst": null,
      "recommendation": "推荐",
      "target_price": null,
      "report_id": null
    },
    {
      "ts_code": "603233.SH",
      "name": "大参林",
      "report_date": "20260513",
      "report_title": "大参林2025年报及2026年一季报点评：盈利能力持续改善，大举分红回报股东",
      "report_type": "点评",
      "classify": "一般报告",
      "org_name": "华创证券",
      "author_name": "郑辰,高初蕾",
      "quarter": "2027Q4",
      "op_rt": 3251300.0,
      "op_pr": null,
      "tp": 249400.0,
      "np": 166600.0,
      "eps": 1.46,
      "pe": 13.0,
      "rd": null,
      "roe": 20.0,
      "ev_ebitda": 8.0,
      "rating": "推荐",
      "max_price": null,
      "min_price": 25.6,
      "rec_date": "20260513",
      "broker": "华创证券",
      "analyst": null,
      "recommendation": "推荐",
      "target_price": null,
      "report_id": null
    },
    {
      "ts_code": "603233.SH",
      "name": "大参林",
      "report_date": "20260513",
      "report_title": "大参林2025年报及2026年一季报点评：盈利能力持续改善，大举分红回报股东",
      "report_type": "点评",
      "classify": "一般报告",
      "org_name": "华创证券",
      "author_name": "郑辰,高初蕾",
      "quarter": "2028Q4",
      "op_rt": 3565800.0,
      "op_pr": null,
      "tp": 282000.0,
      "np": 188400.0,
      "eps": 1.65,
      "pe": 11.0,
      "rd": null,
      "roe": 21.1,
      "ev_ebitda": 7.0,
      "rating": "推荐",
      "max_price": null,
      "min_price": 25.6,
      "rec_date": "20260513",
      "broker": "华创证券",
      "analyst": null,
      "recommendation": "推荐",
      "target_price": null,
      "report_id": null
    },
    {
      "ts_code": "603233.SH",
      "name": "大参林",
      "report_date": "20260510",
      "report_title": "大参林：2025&26Q1利润端增速亮眼，门店数量稳步扩张",
      "report_type": "点评",
      "classify": "一般报告",
      "org_name": "国信证券",
      "author_name": "陈曦炳,彭思宇,贾瑞祥",
      "quarter": "2027Q4",
      "op_rt": 3229800.0,
      "op_pr": null,
      "tp": 250000.0,
      "np": 170800.0,
      "eps": 1.5,
      "pe": 12.3,
      "rd": 4.9,
      "roe": 19.9,
      "ev_ebitda": 12.6,
      "rating": "优于大市",
      "max_price": null,
      "min_price": null,
      "rec_date": "20260510",
      "broker": "国信证券",
      "analyst": null,
      "recommendation": "优于大市",
      "target_price": null,
      "report_id": null
    },
    {
      "ts_code": "603233.SH",
      "name": "大参林",
      "report_date": "20260510",
      "report_title": "大参林：2025&26Q1利润端增速亮眼，门店数量稳步扩张",
      "report_type": "点评",
      "classify": "一般报告",
      "org_name": "国信证券",
      "author_name": "陈曦炳,彭思宇,贾瑞祥",
      "quarter": "2028Q4",
      "op_rt": 3540300.0,
      "op_pr": null,
      "tp": 287800.0,
      "np": 196600.0,
      "eps": 1.73,
      "pe": 10.7,
      "rd": 5.6,
      "roe": 21.0,
      "ev_ebitda": 11.4,
      "rating": "优于大市",
      "max_price": null,
      "min_price": null,
      "rec_date": "20260510",
      "broker": "国信证券",
      "analyst": null,
      "recommendation": "优于大市",
      "target_price": null,
      "report_id": null
    },
    {
      "ts_code": "603233.SH",
      "name": "大参林",
      "report_date": "20260510",
      "report_title": "大参林：2025&26Q1利润端增速亮眼，门店数量稳步扩张",
      "report_type": "点评",
      "classify": "一般报告",
      "org_name": "国信证券",
      "author_name": "陈曦炳,彭思宇,贾瑞祥",
      "quarter": "2026Q4",
      "op_rt": 2950200.0,
      "op_pr": null,
      "tp": 217100.0,
      "np": 148300.0,
      "eps": 1.3,
      "pe": 14.2,
      "rd": 4.6,
      "roe": 18.8,
      "ev_ebitda": 14.1,
      "rating": "优于大市",
      "max_price": null,
      "min_price": null,
      "rec_date": "20260510",
      "broker": "国信证券",
      "analyst": null,
      "recommendation": "优于大市",
      "target_price": null,
      "report_id": null
    },
    {
      "ts_code": "603233.SH",
      "name": "大参林",
      "report_date": "20260509",
      "report_title": "大参林：盈利能力稳步向好，25年分红比例维持高位",
      "report_type": "点评",
      "classify": "一般报告",
      "org_name": "中信建投",
      "author_name": "袁清慧,刘若飞,沈兴熙,袁全,贺菊颖",
      "quarter": "2026Q4",
      "op_rt": 3025500.0,
      "op_pr": null,
      "tp": null,
      "np": 148300.0,
      "eps": 1.3,
      "pe": 14.0,
      "rd": null,
      "roe": 18.2,
      "ev_ebitda": null,
      "rating": "买入",
      "max_price": null,
      "min_price": null,
      "rec_date": "20260509",
      "broker": "中信建投",
      "analyst": null,
      "recommendation": "买入",
      "target_price": null,
      "report_id": null
    },
    {
      "ts_code": "603233.SH",
      "name": "大参林",
      "report_date": "20260509",
      "report_title": "大参林：盈利能力稳步向好，25年分红比例维持高位",
      "report_type": "点评",
      "classify": "一般报告",
      "org_name": "中信建投",
      "author_name": "袁清慧,刘若飞,沈兴熙,袁全,贺菊颖",
      "quarter": "2027Q4",
      "op_rt": 3336400.0,
      "op_pr": null,
      "tp": null,
      "np": 170800.0,
      "eps": 1.5,
      "pe": 12.1,
      "rd": null,
      "roe": 18.8,
      "ev_ebitda": null,
      "rating": "买入",
      "max_price": null,
      "min_price": null,
      "rec_date": "20260509",
      "broker": "中信建投",
      "analyst": null,
      "recommendation": "买入",
      "target_price": null,
      "report_id": null
    },
    {
      "ts_code": "603233.SH",
      "name": "大参林",
      "report_date": "20260509",
      "report_title": "大参林：盈利能力稳步向好，25年分红比例维持高位",
      "report_type": "点评",
      "classify": "一般报告",
      "org_name": "中信建投",
      "author_name": "袁清慧,刘若飞,沈兴熙,袁全,贺菊颖",
      "quarter": "2028Q4",
      "op_rt": 3682600.0,
      "op_pr": null,
      "tp": null,
      "np": 196800.0,
      "eps": 1.73,
      "pe": 10.5,
      "rd": null,
      "roe": 19.4,
      "ev_ebitda": null,
      "rating": "买入",
      "max_price": null,
      "min_price": null,
      "rec_date": "20260509",
      "broker": "中信建投",
      "analyst": null,
      "recommendation": "买入",
      "target_price": null,
      "report_id": null
    },
    {
      "ts_code": "603233.SH",
      "name": "大参林",
      "report_date": "20260508",
      "report_title": "大参林：利润高速增长，门店深耕持续推进",
      "report_type": "点评",
      "classify": "首份报告",
      "org_name": "兴业证券",
      "author_name": "黄翰漾,孙媛媛,王佳慧,高尹伟业",
      "quarter": "2026Q4",
      "op_rt": 3032300.0,
      "op_pr": null,
      "tp": 222500.0,
      "np": 149700.0,
      "eps": 1.31,
      "pe": 14.1,
      "rd": null,
      "roe": 19.4,
      "ev_ebitda": null,
      "rating": "增持",
      "max_price": null,
      "min_price": null,
      "rec_date": "20260508",
      "broker": "兴业证券",
      "analyst": null,
      "recommendation": "增持",
      "target_price": null,
      "report_id": null
    },
    {
      "ts_code": "603233.SH",
      "name": "大参林",
      "report_date": "20260508",
      "report_title": "大参林：利润高速增长，门店深耕持续推进",
      "report_type": "点评",
      "classify": "首份报告",
      "org_name": "兴业证券",
      "author_name": "黄翰漾,孙媛媛,王佳慧,高尹伟业",
      "quarter": "2027Q4",
      "op_rt": 3280900.0,
      "op_pr": null,
      "tp": 242200.0,
      "np": 162900.0,
      "eps": 1.43,
      "pe": 12.9,
      "rd": null,
      "roe": 20.1,
      "ev_ebitda": null,
      "rating": "增持",
      "max_price": null,
      "min_price": null,
      "rec_date": "20260508",
      "broker": "兴业证券",
      "analyst": null,
      "recommendation": "增持",
      "target_price": null,
      "report_id": null
    },
    {
      "ts_code": "603233.SH",
      "name": "大参林",
      "report_date": "20260508",
      "report_title": "大参林：利润高速增长，门店深耕持续推进",
      "report_type": "点评",
      "classify": "首份报告",
      "org_name": "兴业证券",
      "author_name": "黄翰漾,孙媛媛,王佳慧,高尹伟业",
      "quarter": "2028Q4",
      "op_rt": 3780400.0,
      "op_pr": null,
      "tp": 278700.0,
      "np": 187400.0,
      "eps": 1.65,
      "pe": 11.2,
      "rd": null,
      "roe": 21.9,
      "ev_ebitda": null,
      "rating": "增持",
      "max_price": null,
      "min_price": null,
      "rec_date": "20260508",
      "broker": "兴业证券",
      "analyst": null,
      "recommendation": "增持",
      "target_price": null,
      "report_id": null
    },
    {
      "ts_code": "603233.SH",
      "name": "大参林",
      "report_date": "20260503",
      "report_title": "大参林2025年年报及2026年一季报点评：业绩略超预期，26Q1重启门店扩张节奏，降本增效推进有望延续利润中高速成长趋势",
      "report_type": "一般",
      "classify": "首份报告",
      "org_name": "中泰证券",
      "author_name": "祝嘉琦,杨涛",
      "quarter": "2026Q4",
      "op_rt": 2901100.0,
      "op_pr": 980000.0,
      "tp": 210900.0,
      "np": 147800.0,
      "eps": 1.3,
      "pe": 14.4,
      "rd": null,
      "roe": 15.9,
      "ev_ebitda": 16.0,
      "rating": "买入",
      "max_price": null,
      "min_price": null,
      "rec_date": "20260503",
      "broker": "中泰证券",
      "analyst": null,
      "recommendation": "买入",
      "target_price": null,
      "report_id": null
    },
    {
      "ts_code": "603233.SH",
      "name": "大参林",
      "report_date": "20260503",
      "report_title": "大参林2025年年报及2026年一季报点评：业绩略超预期，26Q1重启门店扩张节奏，降本增效推进有望延续利润中高速成长趋势",
      "report_type": "一般",
      "classify": "首份报告",
      "org_name": "中泰证券",
      "author_name": "祝嘉琦,杨涛",
      "quarter": "2027Q4",
      "op_rt": 3117500.0,
      "op_pr": 1052000.0,
      "tp": 242300.0,
      "np": 169800.0,
      "eps": 1.49,
      "pe": 12.6,
      "rd": null,
      "roe": 16.6,
      "ev_ebitda": 14.0,
      "rating": "买入",
      "max_price": null,
      "min_price": null,
      "rec_date": "20260503",
      "broker": "中泰证券",
      "analyst": null,
      "recommendation": "买入",
      "target_price": null,
      "report_id": null
    },
    {
      "ts_code": "603233.SH",
      "name": "大参林",
      "report_date": "20260503",
      "report_title": "大参林2025年年报及2026年一季报点评：业绩略超预期，26Q1重启门店扩张节奏，降本增效推进有望延续利润中高速成长趋势",
      "report_type": "一般",
      "classify": "首份报告",
      "org_name": "中泰证券",
      "author_name": "祝嘉琦,杨涛",
      "quarter": "2028Q4",
      "op_rt": 3323200.0,
      "op_pr": 1119000.0,
      "tp": 267200.0,
      "np": 187200.0,
      "eps": 1.64,
      "pe": 11.4,
      "rd": null,
      "roe": 16.6,
      "ev_ebitda": 13.0,
      "rating": "买入",
      "max_price": null,
      "min_price": null,
      "rec_date": "20260503",
      "broker": "中泰证券",
      "analyst": null,
      "recommendation": "买入",
      "target_price": null,
      "report_id": null
    },
    {
      "ts_code": "603233.SH",
      "name": "大参林",
      "report_date": "20260429",
      "report_title": "大参林25年报&26一季报点评：降本增效落地，盈利趋势向好",
      "report_type": "点评",
      "classify": "一般报告",
      "org_name": "东方证券",
      "author_name": "伍云飞,袁润璞",
      "quarter": "2026Q4",
      "op_rt": 2972700.0,
      "op_pr": null,
      "tp": 200600.0,
      "np": 141500.0,
      "eps": 1.24,
      "pe": 15.1,
      "rd": null,
      "roe": 17.4,
      "ev_ebitda": 6.8,
      "rating": "买入",
      "max_price": null,
      "min_price": 26.04,
      "rec_date": "20260429",
      "broker": "东方证券",
      "analyst": null,
      "recommendation": "买入",
      "target_price": null,
      "report_id": null
    },
    {
      "ts_code": "603233.SH",
      "name": "大参林",
      "report_date": "20260429",
      "report_title": "大参林25年报&26一季报点评：降本增效落地，盈利趋势向好",
      "report_type": "点评",
      "classify": "一般报告",
      "org_name": "东方证券",
      "author_name": "伍云飞,袁润璞",
      "quarter": "2028Q4",
      "op_rt": 3592800.0,
      "op_pr": null,
      "tp": 269300.0,
      "np": 188100.0,
      "eps": 1.65,
      "pe": 11.4,
      "rd": null,
      "roe": 18.0,
      "ev_ebitda": 5.3,
      "rating": "买入",
      "max_price": null,
      "min_price": 26.04,
      "rec_date": "20260429",
      "broker": "东方证券",
      "analyst": null,
      "recommendation": "买入",
      "target_price": null,
      "report_id": null
    },
    {
      "ts_code": "603233.SH",
      "name": "大参林",
      "report_date": "20260429",
      "report_title": "大参林25年报&26一季报点评：降本增效落地，盈利趋势向好",
      "report_type": "点评",
      "classify": "一般报告",
      "org_name": "东方证券",
      "author_name": "伍云飞,袁润璞",
      "quarter": "2027Q4",
      "op_rt": 3260200.0,
      "op_pr": null,
      "tp": 233600.0,
      "np": 163100.0,
      "eps": 1.43,
      "pe": 13.1,
      "rd": null,
      "roe": 17.4,
      "ev_ebitda": 5.9,
      "rating": "买入",
      "max_price": null,
      "min_price": 26.04,
      "rec_date": "20260429",
      "broker": "东方证券",
      "analyst": null,
      "recommendation": "买入",
      "target_price": null,
      "report_id": null
    },
    {
      "ts_code": "603233.SH",
      "name": "大参林",
      "report_date": "20260428",
      "report_title": "大参林：利润增长超预期，多举措提升业绩释放潜力",
      "report_type": "点评",
      "classify": "一般报告",
      "org_name": "中邮证券",
      "author_name": "盛丽华,龙永茂",
      "quarter": "2026Q4",
      "op_rt": 3036000.0,
      "op_pr": null,
      "tp": 217400.0,
      "np": 148643.0,
      "eps": 1.31,
      "pe": 13.94,
      "rd": null,
      "roe": 19.2,
      "ev_ebitda": 6.75,
      "rating": "买入",
      "max_price": null,
      "min_price": null,
      "rec_date": "20260428",
      "broker": "中邮证券",
      "analyst": null,
      "recommendation": "买入",
      "target_price": null,
      "report_id": null
    },
    {
      "ts_code": "603233.SH",
      "name": "大参林",
      "report_date": "20260428",
      "report_title": "大参林：利润增长超预期，多举措提升业绩释放潜力",
      "report_type": "点评",
      "classify": "一般报告",
      "org_name": "中邮证券",
      "author_name": "盛丽华,龙永茂",
      "quarter": "2028Q4",
      "op_rt": 3719600.0,
      "op_pr": null,
      "tp": 277300.0,
      "np": 187634.0,
      "eps": 1.65,
      "pe": 11.04,
      "rd": null,
      "roe": 21.9,
      "ev_ebitda": 4.33,
      "rating": "买入",
      "max_price": null,
      "min_price": null,
      "rec_date": "20260428",
      "broker": "中邮证券",
      "analyst": null,
      "recommendation": "买入",
      "target_price": null,
      "report_id": null
    },
    {
      "ts_code": "603233.SH",
      "name": "大参林",
      "report_date": "20260428",
      "report_title": "大参林：利润增长超预期，多举措提升业绩释放潜力",
      "report_type": "点评",
      "classify": "一般报告",
      "org_name": "中邮证券",
      "author_name": "盛丽华,龙永茂",
      "quarter": "2027Q4",
      "op_rt": 3360400.0,
      "op_pr": null,
      "tp": 244300.0,
      "np": 165682.0,
      "eps": 1.45,
      "pe": 12.5,
      "rd": null,
      "roe": 20.4,
      "ev_ebitda": 5.48,
      "rating": "买入",
      "max_price": null,
      "min_price": null,
      "rec_date": "20260428",
      "broker": "中邮证券",
      "analyst": null,
      "recommendation": "买入",
      "target_price": null,
      "report_id": null
    },
    {
      "ts_code": "603233.SH",
      "name": "大参林",
      "report_date": "20260428",
      "report_title": "大参林：1Q26略超预期，门店网络结构性优化赋能增长",
      "report_type": "点评",
      "classify": "一般报告",
      "org_name": "中金",
      "author_name": "李千翊,张琎",
      "quarter": "2026Q4",
      "op_rt": 3026300.0,
      "op_pr": null,
      "tp": 214600.0,
      "np": 148300.0,
      "eps": 1.3,
      "pe": 14.3,
      "rd": 3.5,
      "roe": 19.0,
      "ev_ebitda": 4.3,
      "rating": "跑赢行业",
      "max_price": null,
      "min_price": 24.0,
      "rec_date": "20260428",
      "broker": "中金",
      "analyst": null,
      "recommendation": "跑赢行业",
      "target_price": null,
      "report_id": null
    },
    {
      "ts_code": "603233.SH",
      "name": "大参林",
      "report_date": "20260428",
      "report_title": "大参林：1Q26略超预期，门店网络结构性优化赋能增长",
      "report_type": "点评",
      "classify": "一般报告",
      "org_name": "中金",
      "author_name": "李千翊,张琎",
      "quarter": "2027Q4",
      "op_rt": 3330100.0,
      "op_pr": null,
      "tp": 248000.0,
      "np": 172200.0,
      "eps": 1.51,
      "pe": 12.3,
      "rd": 4.1,
      "roe": 19.7,
      "ev_ebitda": 3.5,
      "rating": "跑赢行业",
      "max_price": null,
      "min_price": 24.0,
      "rec_date": "20260428",
      "broker": "中金",
      "analyst": null,
      "recommendation": "跑赢行业",
      "target_price": null,
      "report_id": null
    },
    {
      "ts_code": "603233.SH",
      "name": "大参林",
      "report_date": "20260427",
      "report_title": "大参林：25年归母净利润增长超35％，26年期待“门店扩张＋经营优化”双轮驱动",
      "report_type": "点评",
      "classify": "一般报告",
      "org_name": "信达证券",
      "author_name": "唐爱金,章钟涛",
      "quarter": "2028Q4",
      "op_rt": 3441000.0,
      "op_pr": null,
      "tp": 272100.0,
      "np": 185700.0,
      "eps": 1.63,
      "pe": 11.15,
      "rd": null,
      "roe": 21.8,
      "ev_ebitda": null,
      "rating": "无",
      "max_price": null,
      "min_price": null,
      "rec_date": "20260427",
      "broker": "信达证券",
      "analyst": null,
      "recommendation": "无",
      "target_price": null,
      "report_id": null
    },
    {
      "ts_code": "603233.SH",
      "name": "大参林",
      "report_date": "20260427",
      "report_title": "大参林：25年归母净利润增长超35％，26年期待“门店扩张＋经营优化”双轮驱动",
      "report_type": "点评",
      "classify": "一般报告",
      "org_name": "信达证券",
      "author_name": "唐爱金,章钟涛",
      "quarter": "2027Q4",
      "op_rt": 3178700.0,
      "op_pr": null,
      "tp": 235300.0,
      "np": 160600.0,
      "eps": 1.41,
      "pe": 12.9,
      "rd": null,
      "roe": 19.9,
      "ev_ebitda": null,
      "rating": "无",
      "max_price": null,
      "min_price": null,
      "rec_date": "20260427",
      "broker": "信达证券",
      "analyst": null,
      "recommendation": "无",
      "target_price": null,
      "report_id": null
    },
    {
      "ts_code": "603233.SH",
      "name": "大参林",
      "report_date": "20260427",
      "report_title": "大参林：25年归母净利润增长超35％，26年期待“门店扩张＋经营优化”双轮驱动",
      "report_type": "点评",
      "classify": "一般报告",
      "org_name": "信达证券",
      "author_name": "唐爱金,章钟涛",
      "quarter": "2026Q4",
      "op_rt": 2927500.0,
      "op_pr": null,
      "tp": 203500.0,
      "np": 138900.0,
      "eps": 1.22,
      "pe": 14.91,
      "rd": null,
      "roe": 18.0,
      "ev_ebitda": null,
      "rating": "无",
      "max_price": null,
      "min_price": null,
      "rec_date": "20260427",
      "broker": "信达证券",
      "analyst": null,
      "recommendation": "无",
      "target_price": null,
      "report_id": null
    },
    {
      "ts_code": "603233.SH",
      "name": "大参林",
      "report_date": "20260427",
      "report_title": "大参林2025年年报及2026年一季报点评：2025利润高增，看好盈利能力继续提升",
      "report_type": "点评",
      "classify": "一般报告",
      "org_name": "中信证券",
      "author_name": "张斌斌,宋硕,陈竹",
      "quarter": "2028Q4",
      "op_rt": 3671900.0,
      "op_pr": null,
      "tp": 294200.0,
      "np": 200800.0,
      "eps": 1.76,
      "pe": 10.3,
      "rd": null,
      "roe": 20.2,
      "ev_ebitda": 4.2,
      "rating": "买入",
      "max_price": null,
      "min_price": 24.0,
      "rec_date": "20260427",
      "broker": "中信证券",
      "analyst": null,
      "recommendation": "买入",
      "target_price": null,
      "report_id": null
    },
    {
      "ts_code": "603233.SH",
      "name": "大参林",
      "report_date": "20260427",
      "report_title": "大参林2025年年报及2026年一季报点评：2025利润高增，看好盈利能力继续提升",
      "report_type": "点评",
      "classify": "一般报告",
      "org_name": "中信证券",
      "author_name": "张斌斌,宋硕,陈竹",
      "quarter": "2027Q4",
      "op_rt": 3296500.0,
      "op_pr": null,
      "tp": 257500.0,
      "np": 175700.0,
      "eps": 1.54,
      "pe": 11.8,
      "rd": null,
      "roe": 19.9,
      "ev_ebitda": 4.8,
      "rating": "买入",
      "max_price": null,
      "min_price": 24.0,
      "rec_date": "20260427",
      "broker": "中信证券",
      "analyst": null,
      "recommendation": "买入",
      "target_price": null,
      "report_id": null
    },
    {
      "ts_code": "603233.SH",
      "name": "大参林",
      "report_date": "20260427",
      "report_title": "大参林2025年年报及2026年一季报点评：2025利润高增，看好盈利能力继续提升",
      "report_type": "点评",
      "classify": "一般报告",
      "org_name": "中信证券",
      "author_name": "张斌斌,宋硕,陈竹",
      "quarter": "2026Q4",
      "op_rt": 2979300.0,
      "op_pr": null,
      "tp": 221800.0,
      "np": 151400.0,
      "eps": 1.33,
      "pe": 13.7,
      "rd": null,
      "roe": 19.0,
      "ev_ebitda": 5.8,
      "rating": "买入",
      "max_price": null,
      "min_price": 24.0,
      "rec_date": "20260427",
      "broker": "中信证券",
      "analyst": null,
      "recommendation": "买入",
      "target_price": null,
      "report_id": null
    },
    {
      "ts_code": "603233.SH",
      "name": "大参林",
      "report_date": "20260427",
      "report_title": "DaShenLin＿Pharmaceutical＿Group－A：Profit＿Growth＿Outpaces＿Revenue；Operational＿Leverage＿Accelerating＿as＿Expansion＿Restarts",
      "report_type": "一般",
      "classify": "首次关注",
      "org_name": "摩根大通证券",
      "author_name": "黄旸,赵悦伦,Derek Choi",
      "quarter": "2026Q4",
      "op_rt": 2942600.0,
      "op_pr": 1015000.0,
      "tp": 234100.0,
      "np": 156300.0,
      "eps": 1.37,
      "pe": 13.3,
      "rd": 5.7,
      "roe": 20.5,
      "ev_ebitda": 4.9,
      "rating": "Overweight",
      "max_price": null,
      "min_price": 26.0,
      "rec_date": "20260427",
      "broker": "摩根大通证券",
      "analyst": null,
      "recommendation": "Overweight",
      "target_price": null,
      "report_id": null
    },
    {
      "ts_code": "603233.SH",
      "name": "大参林",
      "report_date": "20260427",
      "report_title": "DaShenLin＿Pharmaceutical＿Group－A：Profit＿Growth＿Outpaces＿Revenue；Operational＿Leverage＿Accelerating＿as＿Expansion＿Restarts",
      "report_type": "一般",
      "classify": "首次关注",
      "org_name": "摩根大通证券",
      "author_name": "黄旸,赵悦伦,Derek Choi",
      "quarter": "2027Q4",
      "op_rt": 3299800.0,
      "op_pr": 1142100.0,
      "tp": 277400.0,
      "np": 185300.0,
      "eps": 1.62,
      "pe": 11.2,
      "rd": 6.8,
      "roe": 22.8,
      "ev_ebitda": 4.3,
      "rating": "Overweight",
      "max_price": null,
      "min_price": 26.0,
      "rec_date": "20260427",
      "broker": "摩根大通证券",
      "analyst": null,
      "recommendation": "Overweight",
      "target_price": null,
      "report_id": null
    },
    {
      "ts_code": "603233.SH",
      "name": "大参林",
      "report_date": "20260427",
      "report_title": "DaShenLin＿Pharmaceutical＿Group－A：Profit＿Growth＿Outpaces＿Revenue；Operational＿Leverage＿Accelerating＿as＿Expansion＿Restarts",
      "report_type": "一般",
      "classify": "首次关注",
      "org_name": "摩根大通证券",
      "author_name": "黄旸,赵悦伦,Derek Choi",
      "quarter": "2028Q4",
      "op_rt": 3643800.0,
      "op_pr": 1260100.0,
      "tp": 313600.0,
      "np": 209500.0,
      "eps": 1.83,
      "pe": 9.9,
      "rd": 7.7,
      "roe": 24.0,
      "ev_ebitda": 3.9,
      "rating": "Overweight",
      "max_price": null,
      "min_price": 26.0,
      "rec_date": "20260427",
      "broker": "摩根大通证券",
      "analyst": null,
      "recommendation": "Overweight",
      "target_price": null,
      "report_id": null
    },
    {
      "ts_code": "603233.SH",
      "name": "大参林",
      "report_date": "20260426",
      "report_title": "大参林2025年报&2026一季报点评：降本增效成果显著，非药盈利能力提升",
      "report_type": "点评",
      "classify": "一般报告",
      "org_name": "东吴证券",
      "author_name": "朱国广,冉胜男,苏丰",
      "quarter": "2026Q4",
      "op_rt": 3048600.0,
      "op_pr": null,
      "tp": 212000.0,
      "np": 149014.0,
      "eps": 1.31,
      "pe": 13.9,
      "rd": null,
      "roe": 16.82,
      "ev_ebitda": null,
      "rating": "买入",
      "max_price": null,
      "min_price": null,
      "rec_date": "20260426",
      "broker": "东吴证券",
      "analyst": null,
      "recommendation": "买入",
      "target_price": null,
      "report_id": null
    },
    {
      "ts_code": "603233.SH",
      "name": "大参林",
      "report_date": "20260426",
      "report_title": "大参林2025年报&2026一季报点评：降本增效成果显著，非药盈利能力提升",
      "report_type": "点评",
      "classify": "一般报告",
      "org_name": "东吴证券",
      "author_name": "朱国广,冉胜男,苏丰",
      "quarter": "2027Q4",
      "op_rt": 3359900.0,
      "op_pr": null,
      "tp": 244300.0,
      "np": 171710.0,
      "eps": 1.51,
      "pe": 12.06,
      "rd": null,
      "roe": 16.24,
      "ev_ebitda": null,
      "rating": "买入",
      "max_price": null,
      "min_price": null,
      "rec_date": "20260426",
      "broker": "东吴证券",
      "analyst": null,
      "recommendation": "买入",
      "target_price": null,
      "report_id": null
    },
    {
      "ts_code": "603233.SH",
      "name": "大参林",
      "report_date": "20260426",
      "report_title": "大参林2025年报&2026一季报点评：降本增效成果显著，非药盈利能力提升",
      "report_type": "点评",
      "classify": "一般报告",
      "org_name": "东吴证券",
      "author_name": "朱国广,冉胜男,苏丰",
      "quarter": "2028Q4",
      "op_rt": 3698900.0,
      "op_pr": null,
      "tp": 281300.0,
      "np": 197771.0,
      "eps": 1.74,
      "pe": 10.47,
      "rd": null,
      "roe": 15.76,
      "ev_ebitda": null,
      "rating": "买入",
      "max_price": null,
      "min_price": null,
      "rec_date": "20260426",
      "broker": "东吴证券",
      "analyst": null,
      "recommendation": "买入",
      "target_price": null,
      "report_id": null
    },
    {
      "ts_code": "603233.SH",
      "name": "大参林",
      "report_date": "20260424",
      "report_title": "大参林：零售毛利率提升，业绩持续向好",
      "report_type": "点评",
      "classify": "一般报告",
      "org_name": "国金证券",
      "author_name": "甘坛焕,王奔奔",
      "quarter": "2026Q4",
      "op_rt": 2895800.0,
      "op_pr": 994700.0,
      "tp": 219900.0,
      "np": 147100.0,
      "eps": 1.292,
      "pe": 13.92,
      "rd": null,
      "roe": 18.97,
      "ev_ebitda": null,
      "rating": "买入",
      "max_price": null,
      "min_price": null,
      "rec_date": "20260424",
      "broker": "国金证券",
      "analyst": null,
      "recommendation": "买入",
      "target_price": null,
      "report_id": null
    },
    {
      "ts_code": "603233.SH",
      "name": "大参林",
      "report_date": "20260424",
      "report_title": "大参林：零售毛利率提升，业绩持续向好",
      "report_type": "点评",
      "classify": "一般报告",
      "org_name": "国金证券",
      "author_name": "甘坛焕,王奔奔",
      "quarter": "2027Q4",
      "op_rt": 3135000.0,
      "op_pr": 1079100.0,
      "tp": 249300.0,
      "np": 166600.0,
      "eps": 1.463,
      "pe": 12.29,
      "rd": null,
      "roe": 20.25,
      "ev_ebitda": null,
      "rating": "买入",
      "max_price": null,
      "min_price": null,
      "rec_date": "20260424",
      "broker": "国金证券",
      "analyst": null,
      "recommendation": "买入",
      "target_price": null,
      "report_id": null
    },
    {
      "ts_code": "603233.SH",
      "name": "大参林",
      "report_date": "20260424",
      "report_title": "大参林：零售毛利率提升，业绩持续向好",
      "report_type": "点评",
      "classify": "一般报告",
      "org_name": "国金证券",
      "author_name": "甘坛焕,王奔奔",
      "quarter": "2028Q4",
      "op_rt": 3390200.0,
      "op_pr": 1168300.0,
      "tp": 281700.0,
      "np": 188100.0,
      "eps": 1.651,
      "pe": 10.89,
      "rd": null,
      "roe": 21.51,
      "ev_ebitda": null,
      "rating": "买入",
      "max_price": null,
      "min_price": null,
      "rec_date": "20260424",
      "broker": "国金证券",
      "analyst": null,
      "recommendation": "买入",
      "target_price": null,
      "report_id": null
    }
  ],
  "summary": {
    "total_90d": 46,
    "unique_brokers_90d": 15,
    "latest_recommendation": "Buy",
    "avg_target_price": null,
    "target_price_count": 0,
    "latest_date": "2026-06-29"
  }
}
