{
  "_meta": {
    "fetched_at": "2026-06-05T05:24:03.021306",
    "version": "4.1",
    "tickers": [
      "300308.SZ",
      "002594.SZ",
      "175.HK",
      "603233.SH"
    ],
    "fx_rates": {
      "HKDCNY": 0.9165
    }
  },
  "yahoo": {
    "300308.SZ": {
      "price": {
        "last": 1226.02,
        "prev_close": 1280,
        "change_pct": -4.217,
        "high": 1301.51,
        "low": 1220.99,
        "volume": 2399583700,
        "avg_volume_20d": null,
        "volume_ratio": null,
        "high_52w": 1301.51,
        "low_52w": 1220.99
      },
      "technical": {
        "sma_20": null,
        "sma_50": null,
        "sma_200": null,
        "rsi_14": null,
        "macd": null,
        "macd_signal": null,
        "macd_histogram": null,
        "above_sma_20": null,
        "above_sma_50": null,
        "above_sma_200": null
      },
      "fundamentals": {
        "market_cap": null,
        "pe_trailing": null,
        "pe_forward": null,
        "ev_ebitda": null,
        "ev_revenue": null,
        "ps_ratio": null,
        "pb": null,
        "dividend_yield": null,
        "revenue": null,
        "revenue_growth": null,
        "gross_margin": null,
        "operating_margin": null,
        "net_margin": null,
        "roe": null,
        "roa": null,
        "debt_to_equity": null,
        "current_ratio": null,
        "quick_ratio": null,
        "free_cash_flow": null,
        "operating_cash_flow": null,
        "total_cash": null,
        "total_debt": null,
        "ebitda": null,
        "earnings_growth": null,
        "book_value": null,
        "enterprise_value": null
      },
      "analyst": {
        "target_mean": null,
        "target_high": null,
        "target_low": null,
        "target_median": null,
        "recommendation": null,
        "num_analysts": null
      },
      "meta": {
        "currency": "",
        "exchange": "SZ",
        "name_en": "Innolight",
        "name_zh": "中际旭创",
        "sector": "",
        "industry": "",
        "website": "",
        "description": ""
      },
      "price_source": "direct_api"
    },
    "002594.SZ": {
      "price": {
        "last": 93.72,
        "prev_close": 93.44,
        "change_pct": 0.3,
        "high": 94,
        "low": 92.3,
        "volume": 2555974300,
        "avg_volume_20d": null,
        "volume_ratio": null,
        "high_52w": 94,
        "low_52w": 92.3
      },
      "technical": {
        "sma_20": null,
        "sma_50": null,
        "sma_200": null,
        "rsi_14": null,
        "macd": null,
        "macd_signal": null,
        "macd_histogram": null,
        "above_sma_20": null,
        "above_sma_50": null,
        "above_sma_200": null
      },
      "fundamentals": {
        "market_cap": null,
        "pe_trailing": null,
        "pe_forward": null,
        "ev_ebitda": null,
        "ev_revenue": null,
        "ps_ratio": null,
        "pb": null,
        "dividend_yield": null,
        "revenue": null,
        "revenue_growth": null,
        "gross_margin": null,
        "operating_margin": null,
        "net_margin": null,
        "roe": null,
        "roa": null,
        "debt_to_equity": null,
        "current_ratio": null,
        "quick_ratio": null,
        "free_cash_flow": null,
        "operating_cash_flow": null,
        "total_cash": null,
        "total_debt": null,
        "ebitda": null,
        "earnings_growth": null,
        "book_value": null,
        "enterprise_value": null
      },
      "analyst": {
        "target_mean": null,
        "target_high": null,
        "target_low": null,
        "target_median": null,
        "recommendation": null,
        "num_analysts": null
      },
      "meta": {
        "currency": "",
        "exchange": "SZ",
        "name_en": "BYD",
        "name_zh": "比亚迪",
        "sector": "",
        "industry": "",
        "website": "",
        "description": ""
      },
      "price_source": "direct_api"
    },
    "175.HK": {
      "price": {
        "last": 18.58,
        "prev_close": 18.64,
        "change_pct": -0.322,
        "high": 18.79,
        "low": 18.38,
        "volume": -80,
        "avg_volume_20d": null,
        "volume_ratio": null,
        "high_52w": 18.79,
        "low_52w": 18.38
      },
      "technical": {
        "sma_20": null,
        "sma_50": null,
        "sma_200": null,
        "rsi_14": null,
        "macd": null,
        "macd_signal": null,
        "macd_histogram": null,
        "above_sma_20": null,
        "above_sma_50": null,
        "above_sma_200": null
      },
      "fundamentals": {
        "market_cap": null,
        "pe_trailing": null,
        "pe_forward": null,
        "ev_ebitda": null,
        "ev_revenue": null,
        "ps_ratio": null,
        "pb": null,
        "dividend_yield": null,
        "revenue": null,
        "revenue_growth": null,
        "gross_margin": null,
        "operating_margin": null,
        "net_margin": null,
        "roe": null,
        "roa": null,
        "debt_to_equity": null,
        "current_ratio": null,
        "quick_ratio": null,
        "free_cash_flow": null,
        "operating_cash_flow": null,
        "total_cash": null,
        "total_debt": null,
        "ebitda": null,
        "earnings_growth": null,
        "book_value": null,
        "enterprise_value": null
      },
      "analyst": {
        "target_mean": null,
        "target_high": null,
        "target_low": null,
        "target_median": null,
        "recommendation": null,
        "num_analysts": null
      },
      "meta": {
        "currency": "",
        "exchange": "HK",
        "name_en": "Geely Auto",
        "name_zh": "吉利汽车",
        "sector": "",
        "industry": "",
        "website": "",
        "description": ""
      },
      "price_source": "direct_api"
    },
    "603233.SH": {
      "price": {
        "last": 16.09,
        "prev_close": 16.08,
        "change_pct": 0.062,
        "high": 16.39,
        "low": 15.96,
        "volume": 364507600,
        "avg_volume_20d": null,
        "volume_ratio": null,
        "high_52w": 16.39,
        "low_52w": 15.96
      },
      "technical": {
        "sma_20": null,
        "sma_50": null,
        "sma_200": null,
        "rsi_14": null,
        "macd": null,
        "macd_signal": null,
        "macd_histogram": null,
        "above_sma_20": null,
        "above_sma_50": null,
        "above_sma_200": null
      },
      "fundamentals": {
        "market_cap": null,
        "pe_trailing": null,
        "pe_forward": null,
        "ev_ebitda": null,
        "ev_revenue": null,
        "ps_ratio": null,
        "pb": null,
        "dividend_yield": null,
        "revenue": null,
        "revenue_growth": null,
        "gross_margin": null,
        "operating_margin": null,
        "net_margin": null,
        "roe": null,
        "roa": null,
        "debt_to_equity": null,
        "current_ratio": null,
        "quick_ratio": null,
        "free_cash_flow": null,
        "operating_cash_flow": null,
        "total_cash": null,
        "total_debt": null,
        "ebitda": null,
        "earnings_growth": null,
        "book_value": null,
        "enterprise_value": null
      },
      "analyst": {
        "target_mean": null,
        "target_high": null,
        "target_low": null,
        "target_median": null,
        "recommendation": null,
        "num_analysts": null
      },
      "meta": {
        "currency": "",
        "exchange": "SH",
        "name_en": "Da Shenlin",
        "name_zh": "大参林",
        "sector": "",
        "industry": "",
        "website": "",
        "description": ""
      },
      "price_source": "direct_api"
    }
  },
  "consensus": {},
  "akshare": {
    "northbound": {},
    "southbound": {
      "latest_net_flow": -3.1493,
      "5d_cumulative": 271.3161,
      "20d_cumulative": 302.584,
      "trend": "inflow",
      "updated": "2026-06-05"
    },
    "dragon_tiger": [
      {
        "code": "000010",
        "name": "*ST美丽",
        "date": "",
        "reason": "连续三个交易日内，涨幅偏离值累计达到12%的ST证券、*ST证券和未完成股改证券",
        "buy_amt": null,
        "sell_amt": null,
        "net_amt": null,
        "focus": false
      },
      {
        "code": "000037",
        "name": "深南电A",
        "date": "",
        "reason": "日换手率达到20%的前5只证券",
        "buy_amt": null,
        "sell_amt": null,
        "net_amt": null,
        "focus": false
      },
      {
        "code": "000037",
        "name": "深南电A",
        "date": "",
        "reason": "连续三个交易日内，涨幅偏离值累计达到20%的证券",
        "buy_amt": null,
        "sell_amt": null,
        "net_amt": null,
        "focus": false
      },
      {
        "code": "000055",
        "name": "方大集团",
        "date": "",
        "reason": "连续三个交易日内，涨幅偏离值累计达到20%的证券",
        "buy_amt": null,
        "sell_amt": null,
        "net_amt": null,
        "focus": false
      },
      {
        "code": "000062",
        "name": "深圳华强",
        "date": "",
        "reason": "日涨幅偏离值达到7%的前5只证券",
        "buy_amt": null,
        "sell_amt": null,
        "net_amt": null,
        "focus": false
      },
      {
        "code": "000078",
        "name": "ST海王",
        "date": "",
        "reason": "连续三个交易日内，涨幅偏离值累计达到12%的ST证券、*ST证券和未完成股改证券",
        "buy_amt": null,
        "sell_amt": null,
        "net_amt": null,
        "focus": false
      },
      {
        "code": "000509",
        "name": "华塑控股",
        "date": "",
        "reason": "日振幅值达到15%的前5只证券",
        "buy_amt": null,
        "sell_amt": null,
        "net_amt": null,
        "focus": false
      },
      {
        "code": "000539",
        "name": "粤电力A",
        "date": "",
        "reason": "日振幅值达到15%的前5只证券",
        "buy_amt": null,
        "sell_amt": null,
        "net_amt": null,
        "focus": false
      },
      {
        "code": "000539",
        "name": "粤电力A",
        "date": "",
        "reason": "日涨幅偏离值达到7%的前5只证券",
        "buy_amt": null,
        "sell_amt": null,
        "net_amt": null,
        "focus": false
      },
      {
        "code": "000539",
        "name": "粤电力A",
        "date": "",
        "reason": "连续三个交易日内，涨幅偏离值累计达到20%的证券",
        "buy_amt": null,
        "sell_amt": null,
        "net_amt": null,
        "focus": false
      },
      {
        "code": "000582",
        "name": "北部湾港",
        "date": "",
        "reason": "日跌幅偏离值达到7%的前5只证券",
        "buy_amt": null,
        "sell_amt": null,
        "net_amt": null,
        "focus": false
      },
      {
        "code": "000601",
        "name": "韶能股份",
        "date": "",
        "reason": "日换手率达到20%的前5只证券",
        "buy_amt": null,
        "sell_amt": null,
        "net_amt": null,
        "focus": false
      },
      {
        "code": "000636",
        "name": "风华高科",
        "date": "",
        "reason": "日振幅值达到15%的前5只证券",
        "buy_amt": null,
        "sell_amt": null,
        "net_amt": null,
        "focus": false
      },
      {
        "code": "000700",
        "name": "模塑科技",
        "date": "",
        "reason": "连续三个交易日内，涨幅偏离值累计达到20%的证券",
        "buy_amt": null,
        "sell_amt": null,
        "net_amt": null,
        "focus": false
      },
      {
        "code": "000700",
        "name": "模塑科技",
        "date": "",
        "reason": "日涨幅偏离值达到7%的前5只证券",
        "buy_amt": null,
        "sell_amt": null,
        "net_amt": null,
        "focus": false
      },
      {
        "code": "000712",
        "name": "锦龙股份",
        "date": "",
        "reason": "日跌幅偏离值达到7%的前5只证券",
        "buy_amt": null,
        "sell_amt": null,
        "net_amt": null,
        "focus": false
      },
      {
        "code": "000722",
        "name": "湖南发展",
        "date": "",
        "reason": "连续三个交易日内，涨幅偏离值累计达到20%的证券",
        "buy_amt": null,
        "sell_amt": null,
        "net_amt": null,
        "focus": false
      },
      {
        "code": "000725",
        "name": "京东方A",
        "date": "",
        "reason": "日涨幅偏离值达到7%的前5只证券",
        "buy_amt": null,
        "sell_amt": null,
        "net_amt": null,
        "focus": false
      },
      {
        "code": "000733",
        "name": "振华科技",
        "date": "",
        "reason": "日涨幅偏离值达到7%的前5只证券",
        "buy_amt": null,
        "sell_amt": null,
        "net_amt": null,
        "focus": false
      },
      {
        "code": "000759",
        "name": "中百集团",
        "date": "",
        "reason": "日跌幅偏离值达到7%的前5只证券",
        "buy_amt": null,
        "sell_amt": null,
        "net_amt": null,
        "focus": false
      },
      {
        "code": "000767",
        "name": "晋控电力",
        "date": "",
        "reason": "日振幅值达到15%的前5只证券",
        "buy_amt": null,
        "sell_amt": null,
        "net_amt": null,
        "focus": false
      },
      {
        "code": "000767",
        "name": "晋控电力",
        "date": "",
        "reason": "日换手率达到20%的前5只证券",
        "buy_amt": null,
        "sell_amt": null,
        "net_amt": null,
        "focus": false
      },
      {
        "code": "000767",
        "name": "晋控电力",
        "date": "",
        "reason": "日涨幅偏离值达到7%的前5只证券",
        "buy_amt": null,
        "sell_amt": null,
        "net_amt": null,
        "focus": false
      },
      {
        "code": "000767",
        "name": "晋控电力",
        "date": "",
        "reason": "连续三个交易日内，涨幅偏离值累计达到20%的证券",
        "buy_amt": null,
        "sell_amt": null,
        "net_amt": null,
        "focus": false
      },
      {
        "code": "000802",
        "name": "北京文化",
        "date": "",
        "reason": "日振幅值达到15%的前5只证券",
        "buy_amt": null,
        "sell_amt": null,
        "net_amt": null,
        "focus": false
      },
      {
        "code": "000903",
        "name": "ST云动",
        "date": "",
        "reason": "连续三个交易日内，涨幅偏离值累计达到12%的ST证券、*ST证券和未完成股改证券",
        "buy_amt": null,
        "sell_amt": null,
        "net_amt": null,
        "focus": false
      },
      {
        "code": "000960",
        "name": "锡业股份",
        "date": "",
        "reason": "日涨幅偏离值达到7%的前5只证券",
        "buy_amt": null,
        "sell_amt": null,
        "net_amt": null,
        "focus": false
      },
      {
        "code": "001210",
        "name": "金房能源",
        "date": "",
        "reason": "连续三个交易日内，涨幅偏离值累计达到20%的证券",
        "buy_amt": null,
        "sell_amt": null,
        "net_amt": null,
        "focus": false
      },
      {
        "code": "001223",
        "name": "欧克科技",
        "date": "",
        "reason": "日振幅值达到15%的前5只证券",
        "buy_amt": null,
        "sell_amt": null,
        "net_amt": null,
        "focus": false
      },
      {
        "code": "001259",
        "name": "利仁科技",
        "date": "",
        "reason": "日跌幅偏离值达到7%的前5只证券",
        "buy_amt": null,
        "sell_amt": null,
        "net_amt": null,
        "focus": false
      },
      {
        "code": "001259",
        "name": "利仁科技",
        "date": "",
        "reason": "日振幅值达到15%的前5只证券",
        "buy_amt": null,
        "sell_amt": null,
        "net_amt": null,
        "focus": false
      },
      {
        "code": "001270",
        "name": "铖昌科技",
        "date": "",
        "reason": "连续三个交易日内，跌幅偏离值累计达到20%的证券",
        "buy_amt": null,
        "sell_amt": null,
        "net_amt": null,
        "focus": false
      },
      {
        "code": "001278",
        "name": "一彬科技",
        "date": "",
        "reason": "日跌幅偏离值达到7%的前5只证券",
        "buy_amt": null,
        "sell_amt": null,
        "net_amt": null,
        "focus": false
      },
      {
        "code": "001309",
        "name": "德明利",
        "date": "",
        "reason": "日涨幅偏离值达到7%的前5只证券",
        "buy_amt": null,
        "sell_amt": null,
        "net_amt": null,
        "focus": false
      },
      {
        "code": "001896",
        "name": "豫能控股",
        "date": "",
        "reason": "日涨幅偏离值达到7%的前5只证券",
        "buy_amt": null,
        "sell_amt": null,
        "net_amt": null,
        "focus": false
      },
      {
        "code": "001896",
        "name": "豫能控股",
        "date": "",
        "reason": "日涨幅偏离值达到7%的前5只证券",
        "buy_amt": null,
        "sell_amt": null,
        "net_amt": null,
        "focus": false
      },
      {
        "code": "001896",
        "name": "豫能控股",
        "date": "",
        "reason": "连续三个交易日内，涨幅偏离值累计达到20%的证券",
        "buy_amt": null,
        "sell_amt": null,
        "net_amt": null,
        "focus": false
      },
      {
        "code": "001896",
        "name": "豫能控股",
        "date": "",
        "reason": "日振幅值达到15%的前5只证券",
        "buy_amt": null,
        "sell_amt": null,
        "net_amt": null,
        "focus": false
      },
      {
        "code": "002046",
        "name": "国机精工",
        "date": "",
        "reason": "日涨幅偏离值达到7%的前5只证券",
        "buy_amt": null,
        "sell_amt": null,
        "net_amt": null,
        "focus": false
      },
      {
        "code": "002055",
        "name": "ST得润",
        "date": "",
        "reason": "连续三个交易日内，跌幅偏离值累计达到12%的ST证券、*ST证券和未完成股改证券",
        "buy_amt": null,
        "sell_amt": null,
        "net_amt": null,
        "focus": false
      },
      {
        "code": "002056",
        "name": "横店东磁",
        "date": "",
        "reason": "连续三个交易日内，涨幅偏离值累计达到20%的证券",
        "buy_amt": null,
        "sell_amt": null,
        "net_amt": null,
        "focus": false
      },
      {
        "code": "002080",
        "name": "中材科技",
        "date": "",
        "reason": "日跌幅偏离值达到7%的前5只证券",
        "buy_amt": null,
        "sell_amt": null,
        "net_amt": null,
        "focus": false
      },
      {
        "code": "002081",
        "name": "金螳螂",
        "date": "",
        "reason": "日换手率达到20%的前5只证券",
        "buy_amt": null,
        "sell_amt": null,
        "net_amt": null,
        "focus": false
      },
      {
        "code": "002081",
        "name": "金螳螂",
        "date": "",
        "reason": "连续三个交易日内，涨幅偏离值累计达到20%的证券",
        "buy_amt": null,
        "sell_amt": null,
        "net_amt": null,
        "focus": false
      },
      {
        "code": "002081",
        "name": "金螳螂",
        "date": "",
        "reason": "日涨幅偏离值达到7%的前5只证券",
        "buy_amt": null,
        "sell_amt": null,
        "net_amt": null,
        "focus": false
      },
      {
        "code": "002082",
        "name": "ST万邦",
        "date": "",
        "reason": "连续三个交易日内，跌幅偏离值累计达到12%的ST证券、*ST证券和未完成股改证券",
        "buy_amt": null,
        "sell_amt": null,
        "net_amt": null,
        "focus": false
      },
      {
        "code": "002137",
        "name": "实益达",
        "date": "",
        "reason": "日换手率达到20%的前5只证券",
        "buy_amt": null,
        "sell_amt": null,
        "net_amt": null,
        "focus": false
      },
      {
        "code": "002137",
        "name": "实益达",
        "date": "",
        "reason": "连续三个交易日内，涨幅偏离值累计达到20%的证券",
        "buy_amt": null,
        "sell_amt": null,
        "net_amt": null,
        "focus": false
      },
      {
        "code": "002156",
        "name": "通富微电",
        "date": "",
        "reason": "日涨幅偏离值达到7%的前5只证券",
        "buy_amt": null,
        "sell_amt": null,
        "net_amt": null,
        "focus": false
      },
      {
        "code": "002167",
        "name": "东方锆业",
        "date": "",
        "reason": "日涨幅偏离值达到7%的前5只证券",
        "buy_amt": null,
        "sell_amt": null,
        "net_amt": null,
        "focus": false
      }
    ],
    "margin": {}
  }
}