{
  "ticker": "300308.SZ",
  "generated_at": "2026-06-23",
  "price": 1382.33,
  "zone": "OVERBOUGHT",
  "entry_zone": true,
  "exit_zone": true,
  "signals": [
    {
      "type": "RSI_OVERBOUGHT",
      "strength": "moderate",
      "date": "20260622",
      "bullish": false,
      "description": {
        "e": "RSI(14) = 73.1 — overbought, watch for exhaustion",
        "z": "RSI(14)=73.1，超买，注意回调风险"
      }
    },
    {
      "type": "BULLISH_ALIGNMENT",
      "strength": "strong",
      "date": "20260622",
      "bullish": true,
      "description": {
        "e": "MA5(1303.9) > MA20(1199.9) > MA60(945.8), price above all — full bullish alignment",
        "z": "MA5(1303.9)>MA20(1199.9)>MA60(945.8)，均线多头排列，趋势强"
      }
    },
    {
      "type": "KDJ_OVERBOUGHT",
      "strength": "strong",
      "date": "20260622",
      "bullish": false,
      "description": {
        "e": "KDJ J=108.2 (extreme >100) — high pullback risk",
        "z": "KDJ J=108.2极度超买，回调风险高"
      }
    }
  ],
  "signal_count": {
    "bullish": 1,
    "bearish": 2,
    "total": 3
  },
  "indicators": {
    "ma5": 1303.88,
    "ma20": 1199.89,
    "ma60": 945.77,
    "rsi14": 73.1,
    "vol_ma20": 294140,
    "vol_ratio": 0.95,
    "price_vs_ma20": 15.21,
    "price_vs_ma60": 46.16,
    "change_1d": 1.06,
    "change_5d": 20.31,
    "change_20d": 33.18,
    "macd_dif": 88.2003,
    "macd_dea": 80.3317,
    "macd_hist": 15.7374,
    "bb_upper": 1362.85,
    "bb_mid": 1199.89,
    "bb_lower": 1036.92,
    "bb_bandwidth": 27.16,
    "kdj_k": 80.5,
    "kdj_d": 66.6,
    "kdj_j": 108.2,
    "cvd_latest": null,
    "cvd_slope_5d": null,
    "cvd_chg_1d": null,
    "cvd_chg_3d": null
  }
}