{
  "ticker": "688120.SH",
  "generated_at": "2026-07-17",
  "price": 258.43,
  "zone": "NEUTRAL",
  "entry_zone": false,
  "exit_zone": true,
  "signals": [
    {
      "type": "MACD_DEATH_CROSS",
      "strength": "moderate",
      "date": "20260716",
      "bullish": false,
      "description": {
        "e": "MACD DIF(15.203) crossed below DEA(18.133) above zero — bearish momentum",
        "z": "MACD DIF(15.203)下穿DEA(18.133)零轴上方死叉看跌"
      }
    }
  ],
  "signal_count": {
    "bullish": 0,
    "bearish": 1,
    "total": 1
  },
  "indicators": {
    "ma5": 301.5,
    "ma20": 283.0,
    "ma60": 248.38,
    "rsi14": 46.0,
    "vol_ma20": 181982,
    "vol_ratio": 0.89,
    "price_vs_ma20": -8.68,
    "price_vs_ma60": 4.05,
    "change_1d": -10.88,
    "change_5d": -24.87,
    "change_20d": 16.25,
    "macd_dif": 15.2032,
    "macd_dea": 18.1331,
    "macd_hist": -5.8597,
    "bb_upper": 353.96,
    "bb_mid": 283.0,
    "bb_lower": 212.05,
    "bb_bandwidth": 50.14,
    "kdj_k": 30.9,
    "kdj_d": 45.0,
    "kdj_j": 2.5,
    "cvd_latest": null,
    "cvd_slope_5d": null,
    "cvd_chg_1d": null,
    "cvd_chg_3d": null
  }
}