{
  "verdict": "PASS",
  "as_of": "2026-07-24T04:19:51.073094+00:00",
  "max_age_days": 2,
  "meta": {
    "fetched_at": "2026-07-23T10:38:02.439092",
    "count": 5526,
    "version": "4.2",
    "scorer": "barra_lite_v1"
  },
  "coverage": {
    "price": 1.0,
    "pe": 0.7369,
    "pb": 0.9924,
    "roe": 0.9763
  },
  "factor_summaries": {
    "value": {
      "coverage": 0.9849800941006153,
      "unique": 955,
      "stdev": 24.307523,
      "median": 55.1
    },
    "quality": {
      "coverage": 0.9849800941006153,
      "unique": 974,
      "stdev": 28.543789,
      "median": 50.0
    },
    "momentum": {
      "coverage": 0.9849800941006153,
      "unique": 1001,
      "stdev": 28.455995,
      "median": 50.0
    },
    "size": {
      "coverage": 0.9849800941006153,
      "unique": 1001,
      "stdev": 28.872875,
      "median": 50.0
    },
    "low_vol": {
      "coverage": 0.9849800941006153,
      "unique": 1001,
      "stdev": 28.873229,
      "median": 50.0
    }
  },
  "errors": [],
  "warnings": [],
  "ticker_checks": []
}
