{
  "date": "2026-04-28",
  "snapshots": [
    {
      "ticker": "300308.SZ",
      "date": "2026-04-28",
      "vp_score": 56,
      "expectation_gap": 10,
      "fundamental_accel": 79,
      "narrative_shift": 72,
      "low_coverage": 50,
      "catalyst_proximity": 80,
      "close": 825,
      "volume": 2951090500,
      "source": "vp_engine",
      "wrongIf_e": "1.6T qualification slips to Q4 2025 OR hyperscaler CapEx cut >20%",
      "wrongIf_z": "1.6T认证推迟至Q4 2025，或超大规模资本支出削减>20%",
      "vp_prev": 56,
      "fa_detail": {
        "score": 79,
        "year_latest": "2025-12-31",
        "year_prior": "2024-12-31",
        "note": "NI/Rev=1.81x  Rev+60%  NI+109% | GM=42.0% (Δ+8.2pp) | FCF/NI=0.75x  FCF=8.1B",
        "components": {
          "ni_rev_score": 78,
          "gm_trend_score": 90,
          "fcf_quality": 72
        },
        "raw": {
          "rev_gr": 60.3,
          "ni_gr": 108.8,
          "ni_rev_ratio": 1.81,
          "gm_pct": 42.0,
          "gm_delta_pp": 8.2,
          "fcf_ni_ratio": 0.75
        }
      },
      "eg_detail": {
        "score": 10,
        "source": "rdcf_delta",
        "signal": "OVERPRICED",
        "delta": -0.814,
        "implied_growth": 115.5,
        "our_growth": 34.1,
        "hyper_growth": true
      },
      "engine_run_at": "2026-04-28T16:22:00.275413+00:00"
    },
    {
      "ticker": "700.HK",
      "date": "2026-04-28",
      "vp_score": 53,
      "expectation_gap": 35,
      "fundamental_accel": 66,
      "narrative_shift": 70,
      "low_coverage": 35,
      "catalyst_proximity": 58,
      "close": 478.6,
      "volume": -100,
      "source": "vp_engine",
      "wrongIf_e": "Regulatory cap on gaming minors extended OR macro consumption weakens sharply",
      "wrongIf_z": "游戏监管扩大或宏观消费急剧恶化",
      "vp_prev": 53,
      "fa_detail": {
        "score": 66,
        "year_latest": "2025-12-31",
        "year_prior": "2024-12-31",
        "note": "NI/Rev=1.14x  Rev+14%  NI+16% | GM=56.2% (Δ+3.3pp) | FCF/NI=0.85x  FCF=190.2B",
        "components": {
          "ni_rev_score": 65,
          "gm_trend_score": 62,
          "fcf_quality": 72
        },
        "raw": {
          "rev_gr": 13.9,
          "ni_gr": 15.9,
          "ni_rev_ratio": 1.14,
          "gm_pct": 56.2,
          "gm_delta_pp": 3.3,
          "fcf_ni_ratio": 0.85
        }
      },
      "eg_detail": {
        "score": 35,
        "source": "rdcf_delta",
        "signal": "OVERPRICED",
        "delta": -0.124,
        "implied_growth": 30.4,
        "our_growth": 18.0,
        "hyper_growth": false
      },
      "engine_run_at": "2026-04-28T16:22:00.276134+00:00"
    },
    {
      "ticker": "9999.HK",
      "date": "2026-04-28",
      "vp_score": 61,
      "expectation_gap": 68,
      "fundamental_accel": 76,
      "narrative_shift": 45,
      "low_coverage": 48,
      "catalyst_proximity": 60,
      "close": 173.3,
      "volume": 11,
      "source": "vp_engine",
      "wrongIf_e": "Marvel Rivals DAU drops below 2M OR Japan MAU misses 3M by Q3 2025",
      "wrongIf_z": "漫威对决DAU低于200万，或日本MAU未达Q3 2025的300万",
      "vp_prev": 61,
      "fa_detail": {
        "score": 76,
        "year_latest": "2025-12-31",
        "year_prior": "2024-12-31",
        "note": "NI/Rev=1.96x  Rev+7%  NI+14% | GM=64.3% (Δ+1.8pp) | FCF/NI=1.44x  FCF=48.7B",
        "components": {
          "ni_rev_score": 78,
          "gm_trend_score": 62,
          "fcf_quality": 88
        },
        "raw": {
          "rev_gr": 7.0,
          "ni_gr": 13.7,
          "ni_rev_ratio": 1.96,
          "gm_pct": 64.3,
          "gm_delta_pp": 1.8,
          "fcf_ni_ratio": 1.44
        }
      },
      "eg_detail": {
        "score": 68,
        "source": "rdcf_delta",
        "signal": "UNDERPRICED",
        "delta": 0.128,
        "implied_growth": 2.2,
        "our_growth": 15.0,
        "hyper_growth": false
      },
      "engine_run_at": "2026-04-28T16:22:00.276823+00:00"
    },
    {
      "ticker": "6160.HK",
      "date": "2026-04-28",
      "vp_score": 51,
      "expectation_gap": 10,
      "fundamental_accel": 57,
      "narrative_shift": 75,
      "low_coverage": 55,
      "catalyst_proximity": 78,
      "close": 180.4,
      "volume": -49,
      "source": "vp_engine",
      "wrongIf_e": "CELESTIAL Phase 3 uMRD data disappoints (<50%) OR pirtobrutinib 1L CLL Phase 3 shows superior PFS",
      "wrongIf_z": "CELESTIAL三期uMRD数据不及预期(<50%)，或多替布鲁替尼1L CLL三期PFS更优",
      "vp_prev": 51,
      "fa_detail": {
        "score": 57,
        "year_latest": "2025-12-31",
        "year_prior": "2024-12-31",
        "note": "NI turnaround or persistent loss | GM=87.5% (Δ+3.1pp) | FCF/NI=3.00x  FCF=0.9B",
        "components": {
          "ni_rev_score": 30,
          "gm_trend_score": 62,
          "fcf_quality": 88
        },
        "raw": {
          "rev_gr": 40.2,
          "ni_gr": null,
          "ni_rev_ratio": null,
          "gm_pct": 87.5,
          "gm_delta_pp": 3.1,
          "fcf_ni_ratio": 3.0
        }
      },
      "eg_detail": {
        "score": 10,
        "source": "rdcf_delta",
        "signal": "OVERPRICED",
        "delta": -0.79,
        "implied_growth": 114.0,
        "our_growth": 35.0,
        "hyper_growth": false
      },
      "engine_run_at": "2026-04-28T16:22:00.277432+00:00"
    },
    {
      "ticker": "002594.SZ",
      "date": "2026-04-28",
      "vp_score": 44,
      "expectation_gap": 78,
      "fundamental_accel": 24,
      "narrative_shift": 38,
      "low_coverage": 32,
      "catalyst_proximity": 45,
      "close": 101.48,
      "volume": 3615500400,
      "source": "vp_engine",
      "wrongIf_e": "EU tariffs on Chinese EVs exceed 35% AND Brazil imposes local content rules",
      "wrongIf_z": "欧盟关税>35%且巴西本地化要求同时触发",
      "vp_prev": 44,
      "fa_detail": {
        "score": 24,
        "year_latest": "2025-12-31",
        "year_prior": "2024-12-31",
        "note": "NI/Rev=-5.49x  Rev+3%  NI+-19% | GM=17.7% (Δ-1.7pp) | FCF/NI=-2.99x  FCF=-97.7B",
        "components": {
          "ni_rev_score": 20,
          "gm_trend_score": 35,
          "fcf_quality": 20
        },
        "raw": {
          "rev_gr": 3.5,
          "ni_gr": -19.0,
          "ni_rev_ratio": -5.49,
          "gm_pct": 17.7,
          "gm_delta_pp": -1.7,
          "fcf_ni_ratio": -2.99
        }
      },
      "eg_detail": {
        "score": 78,
        "source": "rdcf_delta",
        "signal": "UNDERPRICED",
        "delta": 0.42,
        "implied_growth": -14.0,
        "our_growth": 28.0,
        "hyper_growth": false
      },
      "engine_run_at": "2026-04-28T16:22:00.278065+00:00"
    }
  ]
}